book_keeping/__init__.py
book_keeping/adjectives.txt
book_keeping/experiments.py
book_keeping/ids.py
book_keeping/nouns.txt
book_keeping/tee.py
book_keeping/template.md
book_keeping/util.py
book_keeping-0.2.0.dist-info/METADATA
book_keeping-0.2.0.dist-info/WHEEL
book_keeping-0.2.0.dist-info/top_level.txt
book_keeping-0.2.0.dist-info/RECORD
