Metadata-Version: 2.1
Name: book-keeping
Version: 0.2.0
Summary: Track config and results for digital experiments.
Home-page: https://github.com/jla-gardner/book-keeping
Author: John Gardner
License: MIT
Keywords: digital,experiment,record,config
Platform: UNKNOWN
Classifier: License :: OSI Approved :: MIT License
Classifier: Programming Language :: Python :: 3
Classifier: Programming Language :: Python :: 3.7
Requires-Python: >=3.7, <4
